dpamber/__init__.py
dpamber/aparam.py
dpamber/cli.py
dpamber/corr.py
dpamber/disang.py
dpamber/drdq.py
dpamber/model_devi.py
dpamber/qmbuffer.py
dpamber/qmwater_corr.py
dpamber/read_amber.py
dpamber/utils.py
dpamber-0.4.0.dist-info/METADATA
dpamber-0.4.0.dist-info/WHEEL
dpamber-0.4.0.dist-info/entry_points.txt
dpamber-0.4.0.dist-info/top_level.txt
dpamber-0.4.0.dist-info/RECORD
