Metadata-Version: 2.1
Name: dpamber
Version: 0.4.0
Summary: Some useful tools related to Amber and DP.
Project-URL: Homepage, https://github.com/njzjz/dpamber
Classifier: Programming Language :: Python
Classifier: Programming Language :: Python :: 3
Requires-Python: >=3.7
Requires-Dist: numpy
Requires-Dist: dpdata[amber] >=0.2.16
Requires-Dist: tqdm
Requires-Dist: ase
Requires-Dist: scipy
Requires-Dist: parmed <4 ; python_version < "3.8"
Requires-Dist: parmed >=4 ; python_version >= "3.8"
Provides-Extra: dpcpu
Requires-Dist: deepmd-kit[cpu] >=2 ; extra == 'dpcpu'
Provides-Extra: dpgpu
Requires-Dist: deepmd-kit[gpu] >=2 ; extra == 'dpgpu'
Provides-Extra: test
Requires-Dist: pytest ; extra == 'test'
Requires-Dist: pytest-cov ; extra == 'test'
Requires-Dist: pytest-mock ; extra == 'test'
Requires-Dist: deepmd-kit >=2.2.2 ; extra == 'test'
